{
    "created": 1660741299772,
    "updated": 1660741299772,
    "trade": {
        "info": {
            "setTime": {
                "second": 1651660952000,
                "third": null
            },
            "strategyId": "622395aaa0074b70dc573b8a",
            "tennisTournamentId": "626674891a800430234d7d4c",
            "date": 1651618800000,
            "marketInfo": {
                "marketName": "Jabeur v S Halep",
                "marketId": "",
                "marketType": "MATCH_ODDS",
                "eventName": "Match Odds",
                "sport": "TENNIS"
            },
            "executor": [
                "DEMO"
            ],
            "exchange": {
                "name": "DEMO",
                "commission": 0.02
            },
            "note": {
                "description": "",
                "entry": "",
                "exit": "",
                "position": "",
                "mm": "",
                "odds": "",
                "post": ""
            }
        },
        "selections": [
            {
                "selectionN": 0,
                "runnerId": 6161111,
                "runnerName": "Ons Jabeur",
                "winner": true,
                "bsp": 2.68,
                "sets": {
                    "secondSet": 1.48,
                    "thirdSet": null
                },
                "avg": {
                    "back": {
                        "odds": 1.35,
                        "stake": 88.23,
                        "toWin": 30.64,
                        "liability": 88.23
                    },
                    "lay": {
                        "odds": 1.49,
                        "stake": 79.55,
                        "toWin": 79.55,
                        "liability": 39.32
                    }
                }
            },
            {
                "selectionN": 1,
                "runnerId": 4625563,
                "runnerName": "Simona Halep",
                "winner": false,
                "bsp": 1.57,
                "sets": {
                    "secondSet": 3.05,
                    "thirdSet": null
                },
                "avg": {
                    "back": {
                        "odds": 1.73,
                        "stake": 38.2,
                        "toWin": 27.92,
                        "liability": 38.2
                    },
                    "lay": {
                        "odds": 1.55,
                        "stake": 42.55,
                        "toWin": 42.55,
                        "liability": 23.58
                    }
                }
            }
        ],
        "trades": [
            {
                "id": 1,
                "selectionN": 1,
                "type": "lay",
                "odds": 1.74,
                "stake": 10.67,
                "liability": 7.9,
                "ifWin": 10.67,
                "options": "OPEN",
                "condition": {
                    "tennis": {
                        "isTennis": true,
                        "point": {
                            "set1": {
                                "runnerA": 1,
                                "runnerB": 0
                            },
                            "set2": {
                                "runnerA": 0,
                                "runnerB": 0
                            },
                            "set3": {
                                "runnerA": 0,
                                "runnerB": 0
                            },
                            "set4": {
                                "runnerA": 0,
                                "runnerB": 0
                            },
                            "set5": {
                                "runnerA": 0,
                                "runnerB": 0
                            },
                            "currentGame": {
                                "runnerA": "0",
                                "runnerB": "0",
                                "server": "B"
                            }
                        }
                    },
                    "football": {
                        "isFootball": false,
                        "point": {
                            "home": 0,
                            "away": 0
                        }
                    },
                    "horse": {
                        "isHorse": false
                    },
                    "note": null,
                    "time": 1651659005000
                }
            },
            {
                "id": 2,
                "selectionN": 1,
                "type": "back",
                "odds": 1.6,
                "stake": 11.6,
                "liability": 11.6,
                "ifWin": 6.96,
                "options": "CLOSE",
                "condition": {
                    "tennis": {
                        "isTennis": true,
                        "point": {
                            "set1": {
                                "runnerA": 1,
                                "runnerB": 1
                            },
                            "set2": {
                                "runnerA": 0,
                                "runnerB": 0
                            },
                            "set3": {
                                "runnerA": 0,
                                "runnerB": 0
                            },
                            "set4": {
                                "runnerA": 0,
                                "runnerB": 0
                            },
                            "set5": {
                                "runnerA": 0,
                                "runnerB": 0
                            },
                            "currentGame": {
                                "runnerA": "0",
                                "runnerB": "0",
                                "server": "A"
                            }
                        }
                    },
                    "football": {
                        "isFootball": false,
                        "point": {
                            "home": 0,
                            "away": 0
                        }
                    },
                    "horse": {
                        "isHorse": false
                    },
                    "note": null,
                    "time": 1651659194000
                }
            },
            {
                "id": 3,
                "selectionN": 1,
                "type": "lay",
                "odds": 1.36,
                "stake": 21.62,
                "liability": 7.78,
                "ifWin": 21.62,
                "options": "OPEN",
                "condition": {
                    "tennis": {
                        "isTennis": true,
                        "point": {
                            "set1": {
                                "runnerA": 1,
                                "runnerB": 2
                            },
                            "set2": {
                                "runnerA": 0,
                                "runnerB": 0
                            },
                            "set3": {
                                "runnerA": 0,
                                "runnerB": 0
                            },
                            "set4": {
                                "runnerA": 0,
                                "runnerB": 0
                            },
                            "set5": {
                                "runnerA": 0,
                                "runnerB": 0
                            },
                            "currentGame": {
                                "runnerA": "0",
                                "runnerB": "0",
                                "server": "B"
                            }
                        }
                    },
                    "football": {
                        "isFootball": false,
                        "point": {
                            "home": 0,
                            "away": 0
                        }
                    },
                    "horse": {
                        "isHorse": false
                    },
                    "note": null,
                    "time": 1651659744000
                }
            },
            {
                "id": 4,
                "selectionN": 1,
                "type": "back",
                "odds": 1.54,
                "stake": 19.1,
                "liability": 19.1,
                "ifWin": 10.31,
                "options": "CLOSE",
                "condition": {
                    "tennis": {
                        "isTennis": true,
                        "point": {
                            "set1": {
                                "runnerA": 2,
                                "runnerB": 2
                            },
                            "set2": {
                                "runnerA": 0,
                                "runnerB": 0
                            },
                            "set3": {
                                "runnerA": 0,
                                "runnerB": 0
                            },
                            "set4": {
                                "runnerA": 0,
                                "runnerB": 0
                            },
                            "set5": {
                                "runnerA": 0,
                                "runnerB": 0
                            },
                            "currentGame": {
                                "runnerA": "0",
                                "runnerB": "0",
                                "server": "A"
                            }
                        }
                    },
                    "football": {
                        "isFootball": false,
                        "point": {
                            "home": 0,
                            "away": 0
                        }
                    },
                    "horse": {
                        "isHorse": false
                    },
                    "note": null,
                    "time": 1651660019000
                }
            },
            {
                "id": 5,
                "selectionN": 1,
                "type": "lay",
                "odds": 1.77,
                "stake": 10.26,
                "liability": 7.9,
                "ifWin": 10.26,
                "options": "OPEN",
                "condition": {
                    "tennis": {
                        "isTennis": true,
                        "point": {
                            "set1": {
                                "runnerA": 3,
                                "runnerB": 2
                            },
                            "set2": {
                                "runnerA": 0,
                                "runnerB": 0
                            },
                            "set3": {
                                "runnerA": 0,
                                "runnerB": 0
                            },
                            "set4": {
                                "runnerA": 0,
                                "runnerB": 0
                            },
                            "set5": {
                                "runnerA": 0,
                                "runnerB": 0
                            },
                            "currentGame": {
                                "runnerA": "0",
                                "runnerB": "0",
                                "server": "B"
                            }
                        }
                    },
                    "football": {
                        "isFootball": false,
                        "point": {
                            "home": 0,
                            "away": 0
                        }
                    },
                    "horse": {
                        "isHorse": false
                    },
                    "note": null,
                    "time": 1651660145000
                }
            },
            {
                "id": 6,
                "selectionN": 0,
                "type": "lay",
                "odds": 1.71,
                "stake": 11.11,
                "liability": 7.89,
                "ifWin": 11.11,
                "options": "OPEN",
                "condition": {
                    "tennis": {
                        "isTennis": true,
                        "point": {
                            "set1": {
                                "runnerA": 4,
                                "runnerB": 2
                            },
                            "set2": {
                                "runnerA": 0,
                                "runnerB": 0
                            },
                            "set3": {
                                "runnerA": 0,
                                "runnerB": 0
                            },
                            "set4": {
                                "runnerA": 0,
                                "runnerB": 0
                            },
                            "set5": {
                                "runnerA": 0,
                                "runnerB": 0
                            },
                            "currentGame": {
                                "runnerA": "0",
                                "runnerB": "0",
                                "server": "A"
                            }
                        }
                    },
                    "football": {
                        "isFootball": false,
                        "point": {
                            "home": 0,
                            "away": 0
                        }
                    },
                    "horse": {
                        "isHorse": false
                    },
                    "note": null,
                    "time": 1651660339000
                }
            },
            {
                "id": 7,
                "selectionN": 1,
                "type": "back",
                "odds": 2.42,
                "stake": 7.5,
                "liability": 7.5,
                "ifWin": 10.65,
                "options": "CLOSE",
                "condition": {
                    "tennis": {
                        "isTennis": true,
                        "point": {
                            "set1": {
                                "runnerA": 4,
                                "runnerB": 2
                            },
                            "set2": {
                                "runnerA": 0,
                                "runnerB": 0
                            },
                            "set3": {
                                "runnerA": 0,
                                "runnerB": 0
                            },
                            "set4": {
                                "runnerA": 0,
                                "runnerB": 0
                            },
                            "set5": {
                                "runnerA": 0,
                                "runnerB": 0
                            },
                            "currentGame": {
                                "runnerA": "0",
                                "runnerB": "0",
                                "server": "A"
                            }
                        }
                    },
                    "football": {
                        "isFootball": false,
                        "point": {
                            "home": 0,
                            "away": 0
                        }
                    },
                    "horse": {
                        "isHorse": false
                    },
                    "note": null,
                    "time": 1651660339000
                }
            },
            {
                "id": 8,
                "selectionN": 0,
                "type": "back",
                "odds": 1.49,
                "stake": 12.75,
                "liability": 12.75,
                "ifWin": 6.25,
                "options": "CLOSE",
                "condition": {
                    "tennis": {
                        "isTennis": true,
                        "point": {
                            "set1": {
                                "runnerA": 5,
                                "runnerB": 2
                            },
                            "set2": {
                                "runnerA": 0,
                                "runnerB": 0
                            },
                            "set3": {
                                "runnerA": 0,
                                "runnerB": 0
                            },
                            "set4": {
                                "runnerA": 0,
                                "runnerB": 0
                            },
                            "set5": {
                                "runnerA": 0,
                                "runnerB": 0
                            },
                            "currentGame": {
                                "runnerA": "0",
                                "runnerB": "0",
                                "server": "B"
                            }
                        }
                    },
                    "football": {
                        "isFootball": false,
                        "point": {
                            "home": 0,
                            "away": 0
                        }
                    },
                    "horse": {
                        "isHorse": false
                    },
                    "note": null,
                    "time": 1651660454000
                }
            },
            {
                "id": 9,
                "selectionN": 0,
                "type": "lay",
                "odds": 1.57,
                "stake": 13.79,
                "liability": 7.86,
                "ifWin": 13.79,
                "options": "OPEN",
                "condition": {
                    "tennis": {
                        "isTennis": true,
                        "point": {
                            "set1": {
                                "runnerA": 5,
                                "runnerB": 3
                            },
                            "set2": {
                                "runnerA": 0,
                                "runnerB": 0
                            },
                            "set3": {
                                "runnerA": 0,
                                "runnerB": 0
                            },
                            "set4": {
                                "runnerA": 0,
                                "runnerB": 0
                            },
                            "set5": {
                                "runnerA": 0,
                                "runnerB": 0
                            },
                            "currentGame": {
                                "runnerA": "0",
                                "runnerB": "0",
                                "server": "A"
                            }
                        }
                    },
                    "football": {
                        "isFootball": false,
                        "point": {
                            "home": 0,
                            "away": 0
                        }
                    },
                    "horse": {
                        "isHorse": false
                    },
                    "note": null,
                    "time": 1651660705000
                }
            },
            {
                "id": 10,
                "selectionN": 0,
                "type": "back",
                "odds": 1.48,
                "stake": 14.63,
                "liability": 14.63,
                "ifWin": 7.02,
                "options": "CLOSE",
                "condition": {
                    "tennis": {
                        "isTennis": true,
                        "point": {
                            "set1": {
                                "runnerA": 6,
                                "runnerB": 3
                            },
                            "set2": {
                                "runnerA": 0,
                                "runnerB": 0
                            },
                            "set3": {
                                "runnerA": 0,
                                "runnerB": 0
                            },
                            "set4": {
                                "runnerA": 0,
                                "runnerB": 0
                            },
                            "set5": {
                                "runnerA": 0,
                                "runnerB": 0
                            },
                            "currentGame": {
                                "runnerA": "0",
                                "runnerB": "0",
                                "server": "B"
                            }
                        }
                    },
                    "football": {
                        "isFootball": false,
                        "point": {
                            "home": 0,
                            "away": 0
                        }
                    },
                    "horse": {
                        "isHorse": false
                    },
                    "note": null,
                    "time": 1651660955000
                }
            },
            {
                "id": 11,
                "selectionN": 0,
                "type": "lay",
                "odds": 1.66,
                "stake": 12.12,
                "liability": 8.0,
                "ifWin": 12.12,
                "options": "OPEN",
                "condition": {
                    "tennis": {
                        "isTennis": true,
                        "point": {
                            "set1": {
                                "runnerA": 6,
                                "runnerB": 3
                            },
                            "set2": {
                                "runnerA": 0,
                                "runnerB": 1
                            },
                            "set3": {
                                "runnerA": 0,
                                "runnerB": 0
                            },
                            "set4": {
                                "runnerA": 0,
                                "runnerB": 0
                            },
                            "set5": {
                                "runnerA": 0,
                                "runnerB": 0
                            },
                            "currentGame": {
                                "runnerA": "0",
                                "runnerB": "0",
                                "server": "A"
                            }
                        }
                    },
                    "football": {
                        "isFootball": false,
                        "point": {
                            "home": 0,
                            "away": 0
                        }
                    },
                    "horse": {
                        "isHorse": false
                    },
                    "note": null,
                    "time": 1651661210000
                }
            },
            {
                "id": 12,
                "selectionN": 0,
                "type": "back",
                "odds": 1.45,
                "stake": 13.87,
                "liability": 13.87,
                "ifWin": 6.24,
                "options": "CLOSE",
                "condition": {
                    "tennis": {
                        "isTennis": true,
                        "point": {
                            "set1": {
                                "runnerA": 6,
                                "runnerB": 3
                            },
                            "set2": {
                                "runnerA": 1,
                                "runnerB": 1
                            },
                            "set3": {
                                "runnerA": 0,
                                "runnerB": 0
                            },
                            "set4": {
                                "runnerA": 0,
                                "runnerB": 0
                            },
                            "set5": {
                                "runnerA": 0,
                                "runnerB": 0
                            },
                            "currentGame": {
                                "runnerA": "0",
                                "runnerB": "0",
                                "server": "B"
                            }
                        }
                    },
                    "football": {
                        "isFootball": false,
                        "point": {
                            "home": 0,
                            "away": 0
                        }
                    },
                    "horse": {
                        "isHorse": false
                    },
                    "note": null,
                    "time": 1651661338000
                }
            },
            {
                "id": 13,
                "selectionN": 0,
                "type": "lay",
                "odds": 1.61,
                "stake": 12.9,
                "liability": 7.87,
                "ifWin": 12.9,
                "options": "OPEN",
                "condition": {
                    "tennis": {
                        "isTennis": true,
                        "point": {
                            "set1": {
                                "runnerA": 6,
                                "runnerB": 3
                            },
                            "set2": {
                                "runnerA": 1,
                                "runnerB": 2
                            },
                            "set3": {
                                "runnerA": 0,
                                "runnerB": 0
                            },
                            "set4": {
                                "runnerA": 0,
                                "runnerB": 0
                            },
                            "set5": {
                                "runnerA": 0,
                                "runnerB": 0
                            },
                            "currentGame": {
                                "runnerA": "0",
                                "runnerB": "0",
                                "server": "A"
                            }
                        }
                    },
                    "football": {
                        "isFootball": false,
                        "point": {
                            "home": 0,
                            "away": 0
                        }
                    },
                    "horse": {
                        "isHorse": false
                    },
                    "note": null,
                    "time": 1651661477000
                }
            },
            {
                "id": 14,
                "selectionN": 0,
                "type": "back",
                "odds": 1.49,
                "stake": 13.94,
                "liability": 13.94,
                "ifWin": 6.83,
                "options": "CLOSE",
                "condition": {
                    "tennis": {
                        "isTennis": true,
                        "point": {
                            "set1": {
                                "runnerA": 6,
                                "runnerB": 3
                            },
                            "set2": {
                                "runnerA": 2,
                                "runnerB": 2
                            },
                            "set3": {
                                "runnerA": 0,
                                "runnerB": 0
                            },
                            "set4": {
                                "runnerA": 0,
                                "runnerB": 0
                            },
                            "set5": {
                                "runnerA": 0,
                                "runnerB": 0
                            },
                            "currentGame": {
                                "runnerA": "0",
                                "runnerB": "0",
                                "server": "B"
                            }
                        }
                    },
                    "football": {
                        "isFootball": false,
                        "point": {
                            "home": 0,
                            "away": 0
                        }
                    },
                    "horse": {
                        "isHorse": false
                    },
                    "note": null,
                    "time": 1651661821000
                }
            },
            {
                "id": 15,
                "selectionN": 0,
                "type": "lay",
                "odds": 1.26,
                "stake": 29.63,
                "liability": 7.7,
                "ifWin": 29.63,
                "options": "OPEN",
                "condition": {
                    "tennis": {
                        "isTennis": true,
                        "point": {
                            "set1": {
                                "runnerA": 6,
                                "runnerB": 3
                            },
                            "set2": {
                                "runnerA": 3,
                                "runnerB": 2
                            },
                            "set3": {
                                "runnerA": 0,
                                "runnerB": 0
                            },
                            "set4": {
                                "runnerA": 0,
                                "runnerB": 0
                            },
                            "set5": {
                                "runnerA": 0,
                                "runnerB": 0
                            },
                            "currentGame": {
                                "runnerA": "0",
                                "runnerB": "0",
                                "server": "A"
                            }
                        }
                    },
                    "football": {
                        "isFootball": false,
                        "point": {
                            "home": 0,
                            "away": 0
                        }
                    },
                    "horse": {
                        "isHorse": false
                    },
                    "note": null,
                    "time": 1651662011000
                }
            },
            {
                "id": 16,
                "selectionN": 0,
                "type": "back",
                "odds": 1.13,
                "stake": 33.04,
                "liability": 33.04,
                "ifWin": 4.3,
                "options": "CLOSE",
                "condition": {
                    "tennis": {
                        "isTennis": true,
                        "point": {
                            "set1": {
                                "runnerA": 6,
                                "runnerB": 3
                            },
                            "set2": {
                                "runnerA": 4,
                                "runnerB": 2
                            },
                            "set3": {
                                "runnerA": 0,
                                "runnerB": 0
                            },
                            "set4": {
                                "runnerA": 0,
                                "runnerB": 0
                            },
                            "set5": {
                                "runnerA": 0,
                                "runnerB": 0
                            },
                            "currentGame": {
                                "runnerA": "0",
                                "runnerB": "0",
                                "server": "B"
                            }
                        }
                    },
                    "football": {
                        "isFootball": false,
                        "point": {
                            "home": 0,
                            "away": 0
                        }
                    },
                    "horse": {
                        "isHorse": false
                    },
                    "note": null,
                    "time": 1651662497000
                }
            }
        ],
        "results": {
            "grossProfit": -4.33,
            "netProfit": -4.33,
            "maxRisk": -8.0,
            "rr": -0.5413,
            "commissionPaid": 0.0,
            "correctionPl": 0,
            "finalScore": {
                "tennis": {
                    "set1": {
                        "runnerA": 6,
                        "runnerB": 3
                    },
                    "set2": {
                        "runnerA": 6,
                        "runnerB": 2
                    },
                    "set3": {
                        "runnerA": null,
                        "runnerB": null
                    },
                    "set4": {
                        "runnerA": null,
                        "runnerB": null
                    },
                    "set5": {
                        "runnerA": null,
                        "runnerB": null
                    },
                    "currentGame": {
                        "runnerA": null,
                        "runnerB": null,
                        "server": null
                    }
                },
                "football": {
                    "home": 0,
                    "away": 0
                }
            }
        },
        "stats": [
            {
                "runnerId": 6161111,
                "stats1": 66.5,
                "stats2": 40.7,
                "stats3": 57.1,
                "stats4": 82.8,
                "stats5": 41.9,
                "stats6": 25.9,
                "stats7": 10,
                "stats8": 7,
                "stats9": 14,
                "stats10": 0
            },
            {
                "runnerId": 4625563,
                "stats1": 66.7,
                "stats2": 50,
                "stats3": 59.1,
                "stats4": 77.6,
                "stats5": 45.2,
                "stats6": 32.4,
                "stats7": 21,
                "stats8": 1,
                "stats9": 12,
                "stats10": 0
            }
        ],
        "params": [
            {
                "runnerId": 6161111,
                "params1": 0,
                "params2": 0,
                "params3": 0,
                "params4": 0,
                "params5": 0,
                "params6": 0,
                "params7": 0,
                "params8": 0,
                "params9": 0,
                "params10": 0
            },
            {
                "runnerId": 4625563,
                "params1": 0,
                "params2": 0,
                "params3": 0,
                "params4": 0,
                "params5": 0,
                "params6": 0,
                "params7": 0,
                "params8": 0,
                "params9": 0,
                "params10": 0
            }
        ]
    }
}