{
    "created": 1648323871027,
    "updated": 1648323871027,
    "trade": {
        "info": {
            "setTime": {
                "second": null,
                "third": null
            },
            "strategyId": "6223950fa0074b70dc573b5a",
            "tennisTournamentId": "61fe7f62a4eaad5dc977082b",
            "marketInfo": {
                "marketName": "Gerasimov v F Auger-Aliassime",
                "marketId": "",
                "marketType": "MATCH_ODDS",
                "eventName": "Match Odds",
                "sport": "TENNIS"
            },
            "executor": [
                "KITO"
            ],
            "exchange": {
                "name": "UK",
                "commission": 0.02
            },
            "note": {
                "description": "",
                "entry": "girata tutta, pollata a non aver fatto uguale agli altri.",
                "exit": "",
                "position": "",
                "mm": "",
                "odds": "",
                "post": ""
            }
        },
        "selections": [
            {
                "selectionN": 0,
                "runnerId": 7797772,
                "runnerName": "Egor Gerasimov",
                "winner": false,
                "bsp": 5,
                "sets": {
                    "secondSet": null,
                    "thirdSet": null
                },
                "avg": {
                    "back": {
                        "odds": 0,
                        "stake": 0,
                        "toWin": 0,
                        "liability": 0
                    },
                    "lay": {
                        "odds": 0,
                        "stake": 0,
                        "toWin": 0,
                        "liability": 0
                    }
                }
            },
            {
                "selectionN": 1,
                "runnerId": 12210252,
                "runnerName": "Felix Auger-Aliassime",
                "winner": true,
                "bsp": 1.25,
                "sets": {
                    "secondSet": null,
                    "thirdSet": null
                },
                "avg": {
                    "back": {
                        "odds": 2.38,
                        "stake": 12.22,
                        "toWin": 16.86,
                        "liability": 12.22
                    },
                    "lay": {
                        "odds": 2.58,
                        "stake": 11.27,
                        "toWin": 11.27,
                        "liability": 17.81
                    }
                }
            }
        ],
        "trades": [
            {
                "id": 1,
                "selectionN": 1,
                "type": "back",
                "odds": 2.38,
                "stake": 12.22,
                "liability": 12.22,
                "ifWin": 16.86,
                "options": "OPEN",
                "condition": {
                    "tennis": {
                        "isTennis": true,
                        "point": {
                            "set1": {
                                "runnerA": 6,
                                "runnerB": 3
                            },
                            "set2": {
                                "runnerA": 1,
                                "runnerB": 1
                            },
                            "set3": {
                                "runnerA": 0,
                                "runnerB": 0
                            },
                            "set4": {
                                "runnerA": 0,
                                "runnerB": 0
                            },
                            "set5": {
                                "runnerA": 0,
                                "runnerB": 0
                            },
                            "currentGame": {
                                "runnerA": "",
                                "runnerB": "",
                                "server": "A"
                            }
                        }
                    },
                    "football": {
                        "isFootball": false,
                        "point": {
                            "home": 0,
                            "away": 0
                        }
                    },
                    "horse": {
                        "isHorse": false
                    },
                    "note": "girata tutta, pollata a non aver fatto uguale agli altri.",
                    "time": 1644412039000
                }
            },
            {
                "id": 2,
                "selectionN": 1,
                "type": "lay",
                "odds": 2.58,
                "stake": 11.27,
                "liability": 17.81,
                "ifWin": 11.27,
                "options": "CLOSE",
                "condition": {
                    "tennis": {
                        "isTennis": true,
                        "point": {
                            "set1": {
                                "runnerA": 6,
                                "runnerB": 3
                            },
                            "set2": {
                                "runnerA": 2,
                                "runnerB": 1
                            },
                            "set3": {
                                "runnerA": 0,
                                "runnerB": 0
                            },
                            "set4": {
                                "runnerA": 0,
                                "runnerB": 0
                            },
                            "set5": {
                                "runnerA": 0,
                                "runnerB": 0
                            },
                            "currentGame": {
                                "runnerA": "",
                                "runnerB": "",
                                "server": "B"
                            }
                        }
                    },
                    "football": {
                        "isFootball": false,
                        "point": {
                            "home": 0,
                            "away": 0
                        }
                    },
                    "horse": {
                        "isHorse": false
                    },
                    "note": null,
                    "time": 1644412215000
                }
            }
        ],
        "results": {
            "grossProfit": -0.95,
            "netProfit": -0.95,
            "maxRisk": -12.22,
            "rr": -0.0777,
            "commissionPaid": 0.0,
            "correctionPl": 0,
            "finalScore": {
                "tennis": {
                    "set1": {
                        "runnerA": 6,
                        "runnerB": 3
                    },
                    "set2": {
                        "runnerA": 2,
                        "runnerB": 6
                    },
                    "set3": {
                        "runnerA": 2,
                        "runnerB": 6
                    },
                    "set4": {
                        "runnerA": null,
                        "runnerB": null
                    },
                    "set5": {
                        "runnerA": null,
                        "runnerB": null
                    },
                    "currentGame": {
                        "runnerA": "",
                        "runnerB": "",
                        "server": ""
                    }
                },
                "football": {
                    "home": 0,
                    "away": 0
                }
            }
        },
        "stats": [
            {
                "runnerId": 7797772,
                "stats1": 0,
                "stats2": 0,
                "stats3": 0,
                "stats4": 0,
                "stats5": 0,
                "stats6": 0,
                "stats7": 0,
                "stats8": 0,
                "stats9": 0,
                "stats10": 0
            },
            {
                "runnerId": 12210252,
                "stats1": 0,
                "stats2": 0,
                "stats3": 0,
                "stats4": 0,
                "stats5": 0,
                "stats6": 0,
                "stats7": 0,
                "stats8": 0,
                "stats9": 0,
                "stats10": 0
            }
        ]
    },
    "params": [
        {
            "runnerId": 7797772,
            "params1": 0,
            "params2": 0,
            "params3": 0,
            "params4": 0,
            "params5": 0,
            "params6": 0,
            "params7": 0,
            "params8": 0,
            "params9": 0,
            "params10": 0
        },
        {
            "runnerId": 12210252,
            "params1": 0,
            "params2": 0,
            "params3": 0,
            "params4": 0,
            "params5": 0,
            "params6": 0,
            "params7": 0,
            "params8": 0,
            "params9": 0,
            "params10": 0
        }
    ]
}