{
    "created": 1660741034112,
    "updated": 1660741034112,
    "trade": {
        "info": {
            "setTime": {
                "second": 1650979902000,
                "third": null
            },
            "strategyId": "62534c6e56114c0a8ba2002b",
            "tennisTournamentId": "626673831a800430234d7d3c",
            "date": 1650927600000,
            "marketInfo": {
                "marketName": "Er Kirkin v c stebe",
                "marketId": "",
                "marketType": "MATCH_ODDS",
                "eventName": "Match Odds",
                "sport": "TENNIS"
            },
            "executor": [
                "DEMO"
            ],
            "exchange": {
                "name": "DEMO",
                "commission": 0.02
            },
            "note": {
                "description": "",
                "entry": "",
                "exit": "",
                "position": "",
                "mm": "",
                "odds": "",
                "post": ""
            }
        },
        "selections": [
            {
                "selectionN": 0,
                "runnerId": 9633532,
                "runnerName": "Ergi Kirkin",
                "winner": true,
                "bsp": 2.68,
                "sets": {
                    "secondSet": 1.46,
                    "thirdSet": null
                },
                "avg": {
                    "back": {
                        "odds": 0,
                        "stake": 0,
                        "toWin": 0,
                        "liability": 0
                    },
                    "lay": {
                        "odds": 0,
                        "stake": 0,
                        "toWin": 0,
                        "liability": 0
                    }
                }
            },
            {
                "selectionN": 1,
                "runnerId": 44519331,
                "runnerName": "C Stebe",
                "winner": false,
                "bsp": 1.59,
                "sets": {
                    "secondSet": 3.1,
                    "thirdSet": null
                },
                "avg": {
                    "back": {
                        "odds": 3.05,
                        "stake": 10,
                        "toWin": 20.5,
                        "liability": 10
                    },
                    "lay": {
                        "odds": 5.0,
                        "stake": 6.1,
                        "toWin": 6.1,
                        "liability": 24.4
                    }
                }
            }
        ],
        "trades": [
            {
                "id": 1,
                "selectionN": 1,
                "type": "back",
                "odds": 3.05,
                "stake": 10.0,
                "liability": 10.0,
                "ifWin": 20.5,
                "options": "OPEN",
                "condition": {
                    "tennis": {
                        "isTennis": true,
                        "point": {
                            "set1": {
                                "runnerA": 6,
                                "runnerB": 4
                            },
                            "set2": {
                                "runnerA": 0,
                                "runnerB": 0
                            },
                            "set3": {
                                "runnerA": 0,
                                "runnerB": 0
                            },
                            "set4": {
                                "runnerA": 0,
                                "runnerB": 0
                            },
                            "set5": {
                                "runnerA": 0,
                                "runnerB": 0
                            },
                            "currentGame": {
                                "runnerA": "0",
                                "runnerB": "0",
                                "server": "A"
                            }
                        }
                    },
                    "football": {
                        "isFootball": false,
                        "point": {
                            "home": 0,
                            "away": 0
                        }
                    },
                    "horse": {
                        "isHorse": false
                    },
                    "note": null,
                    "time": 1650979905000
                }
            },
            {
                "id": 2,
                "selectionN": 1,
                "type": "lay",
                "odds": 5.0,
                "stake": 6.1,
                "liability": 24.4,
                "ifWin": 6.1,
                "options": "CLOSE",
                "condition": {
                    "tennis": {
                        "isTennis": true,
                        "point": {
                            "set1": {
                                "runnerA": 6,
                                "runnerB": 4
                            },
                            "set2": {
                                "runnerA": 5,
                                "runnerB": 4
                            },
                            "set3": {
                                "runnerA": 0,
                                "runnerB": 0
                            },
                            "set4": {
                                "runnerA": 0,
                                "runnerB": 0
                            },
                            "set5": {
                                "runnerA": 0,
                                "runnerB": 0
                            },
                            "currentGame": {
                                "runnerA": "0",
                                "runnerB": "0",
                                "server": "B"
                            }
                        }
                    },
                    "football": {
                        "isFootball": false,
                        "point": {
                            "home": 0,
                            "away": 0
                        }
                    },
                    "horse": {
                        "isHorse": false
                    },
                    "note": null,
                    "time": 1650982498000
                }
            }
        ],
        "results": {
            "grossProfit": -3.9,
            "netProfit": -3.9,
            "maxRisk": -10.0,
            "rr": -0.39,
            "commissionPaid": 0.0,
            "correctionPl": 0,
            "finalScore": {
                "tennis": {
                    "set1": {
                        "runnerA": 6,
                        "runnerB": 4
                    },
                    "set2": {
                        "runnerA": 7,
                        "runnerB": 6
                    },
                    "set3": {
                        "runnerA": null,
                        "runnerB": null
                    },
                    "set4": {
                        "runnerA": null,
                        "runnerB": null
                    },
                    "set5": {
                        "runnerA": null,
                        "runnerB": null
                    },
                    "currentGame": {
                        "runnerA": null,
                        "runnerB": null,
                        "server": null
                    }
                },
                "football": {
                    "home": 0,
                    "away": 0
                }
            }
        },
        "stats": [
            {
                "runnerId": 9633532,
                "stats1": 0,
                "stats2": 0,
                "stats3": 0,
                "stats4": 0,
                "stats5": 0,
                "stats6": 0,
                "stats7": 0,
                "stats8": 0,
                "stats9": 0,
                "stats10": 0
            },
            {
                "runnerId": 44519331,
                "stats1": 0,
                "stats2": 0,
                "stats3": 0,
                "stats4": 0,
                "stats5": 0,
                "stats6": 0,
                "stats7": 0,
                "stats8": 0,
                "stats9": 0,
                "stats10": 0
            }
        ],
        "params": [
            {
                "runnerId": 9633532,
                "params1": 0,
                "params2": 0,
                "params3": 0,
                "params4": 0,
                "params5": 0,
                "params6": 0,
                "params7": 0,
                "params8": 0,
                "params9": 0,
                "params10": 0
            },
            {
                "runnerId": 44519331,
                "params1": 0,
                "params2": 0,
                "params3": 0,
                "params4": 0,
                "params5": 0,
                "params6": 0,
                "params7": 0,
                "params8": 0,
                "params9": 0,
                "params10": 0
            }
        ]
    }
}