{
    "created": 1648583705967,
    "updated": 1648583705967,
    "trade": {
        "info": {
            "setTime": {
                "second": null,
                "third": null
            },
            "strategyId": "62239534a0074b70dc573b6a",
            "tennisTournamentId": "621cea0c5f0415577c9251ec",
            "date": 1646006400000,
            "marketInfo": {
                "marketName": "Escoffier v De Schepper - Set 1 Winner",
                "marketId": "",
                "marketType": "SET_WINNER",
                "eventName": "Set 1 Winner",
                "sport": "TENNIS"
            },
            "executor": [
                "KITO"
            ],
            "exchange": {
                "name": "UK",
                "commission": 0.02
            },
            "note": {
                "description": "",
                "entry": "",
                "exit": "",
                "position": "",
                "mm": "",
                "odds": "",
                "post": ""
            }
        },
        "selections": [
            {
                "selectionN": 0,
                "runnerId": 9454286,
                "runnerName": "Antoine Escoffier",
                "winner": true,
                "bsp": 1.55,
                "sets": {
                    "secondSet": null,
                    "thirdSet": null
                },
                "avg": {
                    "back": {
                        "odds": 0,
                        "stake": 0,
                        "toWin": 0,
                        "liability": 0
                    },
                    "lay": {
                        "odds": 0,
                        "stake": 0,
                        "toWin": 0,
                        "liability": 0
                    }
                }
            },
            {
                "selectionN": 1,
                "runnerId": 5617034,
                "runnerName": "Kenny De Schepper",
                "winner": false,
                "bsp": 1.24,
                "sets": {
                    "secondSet": null,
                    "thirdSet": null
                },
                "avg": {
                    "back": {
                        "odds": 0,
                        "stake": 0,
                        "toWin": 0,
                        "liability": 0
                    },
                    "lay": {
                        "odds": 1.06,
                        "stake": 33.33,
                        "toWin": 33.33,
                        "liability": 2.0
                    }
                }
            }
        ],
        "trades": [
            {
                "id": 1,
                "selectionN": 1,
                "type": "lay",
                "odds": 1.06,
                "stake": 33.33,
                "liability": 2.0,
                "ifWin": 33.33,
                "options": "OPEN",
                "condition": {
                    "tennis": {
                        "isTennis": true,
                        "point": {
                            "set1": {
                                "runnerA": 0,
                                "runnerB": 4
                            },
                            "set2": {
                                "runnerA": 0,
                                "runnerB": 0
                            },
                            "set3": {
                                "runnerA": 0,
                                "runnerB": 0
                            },
                            "set4": {
                                "runnerA": 0,
                                "runnerB": 0
                            },
                            "set5": {
                                "runnerA": 0,
                                "runnerB": 0
                            },
                            "currentGame": {
                                "runnerA": "15",
                                "runnerB": "0",
                                "server": "B"
                            }
                        }
                    },
                    "football": {
                        "isFootball": false,
                        "point": {
                            "home": 0,
                            "away": 0
                        }
                    },
                    "horse": {
                        "isHorse": false
                    },
                    "note": null,
                    "time": 1646053075000
                }
            }
        ],
        "results": {
            "grossProfit": -2.0,
            "netProfit": -2.0,
            "maxRisk": -2.0,
            "rr": -1.0,
            "commissionPaid": 0.0,
            "correctionPl": 0,
            "finalScore": {
                "tennis": {
                    "set1": {
                        "runnerA": 0,
                        "runnerB": 6
                    },
                    "set2": {
                        "runnerA": 6,
                        "runnerB": 4
                    },
                    "set3": {
                        "runnerA": 7,
                        "runnerB": 5
                    },
                    "set4": {
                        "runnerA": null,
                        "runnerB": null
                    },
                    "set5": {
                        "runnerA": null,
                        "runnerB": null
                    },
                    "currentGame": {
                        "runnerA": null,
                        "runnerB": null,
                        "server": null
                    }
                },
                "football": {
                    "home": 0,
                    "away": 0
                }
            }
        },
        "stats": [
            {
                "runnerId": 9454286,
                "stats1": 0,
                "stats2": 0,
                "stats3": 0,
                "stats4": 0,
                "stats5": 0,
                "stats6": 0,
                "stats7": 0,
                "stats8": 0,
                "stats9": 0,
                "stats10": 0
            },
            {
                "runnerId": 5617034,
                "stats1": 0,
                "stats2": 0,
                "stats3": 0,
                "stats4": 0,
                "stats5": 0,
                "stats6": 0,
                "stats7": 0,
                "stats8": 0,
                "stats9": 0,
                "stats10": 0
            }
        ],
        "params": [
            {
                "runnerId": 9454286,
                "params1": 0,
                "params2": 0,
                "params3": 0,
                "params4": 0,
                "params5": 0,
                "params6": 0,
                "params7": 0,
                "params8": 0,
                "params9": 0,
                "params10": 0
            },
            {
                "runnerId": 5617034,
                "params1": 0,
                "params2": 0,
                "params3": 0,
                "params4": 0,
                "params5": 0,
                "params6": 0,
                "params7": 0,
                "params8": 0,
                "params9": 0,
                "params10": 0
            }
        ]
    }
}